quri_parts_oqtopus/__init__.py
quri_parts_oqtopus/py.typed
quri_parts_oqtopus/sampler.py
quri_parts_oqtopus/backend/__init__.py
quri_parts_oqtopus/backend/config.py
quri_parts_oqtopus/backend/device.py
quri_parts_oqtopus/backend/estimation.py
quri_parts_oqtopus/backend/sampling.py
quri_parts_oqtopus/backend/sse.py
quri_parts_oqtopus/backend/utils.py
quri_parts_oqtopus/rest/__init__.py
quri_parts_oqtopus/rest/api_client.py
quri_parts_oqtopus/rest/configuration.py
quri_parts_oqtopus/rest/rest.py
quri_parts_oqtopus/rest/api/__init__.py
quri_parts_oqtopus/rest/api/api_token_api.py
quri_parts_oqtopus/rest/api/device_api.py
quri_parts_oqtopus/rest/api/job_api.py
quri_parts_oqtopus/rest/models/__init__.py
quri_parts_oqtopus/rest/models/api_token_api_token.py
quri_parts_oqtopus/rest/models/devices_device_info.py
quri_parts_oqtopus/rest/models/error_bad_request.py
quri_parts_oqtopus/rest/models/error_forbidden_error.py
quri_parts_oqtopus/rest/models/error_internal_server_error.py
quri_parts_oqtopus/rest/models/error_not_found_error.py
quri_parts_oqtopus/rest/models/error_unauthorized_error.py
quri_parts_oqtopus/rest/models/jobs_estimation_result.py
quri_parts_oqtopus/rest/models/jobs_get_job_status_response.py
quri_parts_oqtopus/rest/models/jobs_get_jobs_response.py
quri_parts_oqtopus/rest/models/jobs_get_sselog_response.py
quri_parts_oqtopus/rest/models/jobs_job_def.py
quri_parts_oqtopus/rest/models/jobs_job_id.py
quri_parts_oqtopus/rest/models/jobs_job_info.py
quri_parts_oqtopus/rest/models/jobs_job_result.py
quri_parts_oqtopus/rest/models/jobs_job_status.py
quri_parts_oqtopus/rest/models/jobs_job_type.py
quri_parts_oqtopus/rest/models/jobs_operator_item.py
quri_parts_oqtopus/rest/models/jobs_sampling_result.py
quri_parts_oqtopus/rest/models/jobs_submit_job_info.py
quri_parts_oqtopus/rest/models/jobs_submit_job_request.py
quri_parts_oqtopus/rest/models/jobs_submit_job_response.py
quri_parts_oqtopus/rest/models/jobs_transpile_result.py
quri_parts_oqtopus-1.0.3.dist-info/METADATA
quri_parts_oqtopus-1.0.3.dist-info/WHEEL
quri_parts_oqtopus-1.0.3.dist-info/licenses/LICENSE
quri_parts_oqtopus-1.0.3.dist-info/RECORD
