Metadata-Version: 2.4
Name: quri-parts-oqtopus
Version: 1.0.3
Summary: QURI Parts OQTOPUS is a library for executing programs on quantum computers via the OQTOPUS Cloud interface.
Project-URL: documentation, https://quri-parts-oqtopus.readthedocs.io/
Project-URL: repository, https://github.com/oqtopus-team/quri-parts-oqtopus
Author-email: oqtopus-team <oqtopus-team@googlegroups.com>
License-Expression: Apache-2.0
License-File: LICENSE
Classifier: Development Status :: 4 - Beta
Classifier: Intended Audience :: Developers
Classifier: Intended Audience :: Science/Research
Classifier: License :: OSI Approved :: Apache Software License
Classifier: Programming Language :: Python
Classifier: Programming Language :: Python :: 3.10
Classifier: Programming Language :: Python :: 3.11
Classifier: Programming Language :: Python :: 3.12
Classifier: Programming Language :: Python :: 3.13
Classifier: Programming Language :: Python :: Implementation :: CPython
Classifier: Programming Language :: Python :: Implementation :: PyPy
Classifier: Topic :: Scientific/Engineering
Classifier: Topic :: Scientific/Engineering :: Physics
Requires-Python: >=3.10
Requires-Dist: certifi
Requires-Dist: quri-parts-circuit>=0.20.3
Requires-Dist: quri-parts-core>=0.20.3
Requires-Dist: quri-parts-openqasm>=0.20.3
Requires-Dist: six>=1.17.0
Requires-Dist: urllib3
